__init__.py
pdf2text.py
simple_pdf2text-0.0.1.dist-info/LICENSE
simple_pdf2text-0.0.1.dist-info/METADATA
simple_pdf2text-0.0.1.dist-info/WHEEL
simple_pdf2text-0.0.1.dist-info/top_level.txt
simple_pdf2text-0.0.1.dist-info/RECORD
