Metadata-Version: 2.1
Name: simple-pdf2text
Version: 0.0.1
Summary: A small package to extract text from pdf
Home-page: https://github.com/OnlyAR/pdf2text
Author: Only(AR)
Author-email: zhangjh.se@outlook.com
Classifier: Programming Language :: Python :: 3
Classifier: License :: OSI Approved :: MIT License
Classifier: Operating System :: OS Independent
Requires-Python: >=3.6
License-File: LICENSE
Requires-Dist: certifi
Requires-Dist: charset-normalizer
Requires-Dist: idna
Requires-Dist: requests
Requires-Dist: tika
Requires-Dist: urllib3
Requires-Dist: wordninja
